[
    {
        "name": "Prjawl katuwal",
        "email": "arbinkc20@gmail.com",
        "password": "$2y$10$vnZWu5GEcmT2ku8D3iND1OD8C95dMrmijB5flQQj0PfQGP5Q69spC"
    },
    {
        "name": "Prjawl katuwal",
        "email": "arbinkc20@gmail.com",
        "password": "$2y$10$y0ciOvhaJZYPUlYDhxbIuuWSvggWfl\/1yzB8VOb1I\/3ACVLiisoUS"
    },
    {
        "name": "Prjawl katuwal",
        "email": "arbinkc20@gmail.com",
        "password": "$2y$10$vV8xeH.trB\/NKknBXgw0aOFgvsh.v1KZnqcZ5qYhn20X3WfjDmsBm"
    },
    {
        "name": "Prjawl katuwal",
        "email": "arbinkc20@gmail.com",
        "password": "$2y$10$Q2zVIE1tiGE7mMCSNd3egebo8ke5EclBYL\/Q82uO.sTRLa8YnG5kq"
    },
    {
        "name": "Jesish raj bistai",
        "email": "jesis@gmail.com",
        "password": "$2y$10$bHsB3ho7\/2WNuhOVizMEOeNiyqfTyEzXqGrDfAk0aDUfKwWM8.8Fm"
    }
]